zorro/__init__.py
zorro/common.py
zorro/evaluate_ZS.py
zorro/operators.py
zorro/parse_zorroscript.py
zorro/price_cache.py
zorro/stockdata.py
lupoclient-0.0.1.dist-info/LICENSE
lupoclient-0.0.1.dist-info/METADATA
lupoclient-0.0.1.dist-info/WHEEL
lupoclient-0.0.1.dist-info/top_level.txt
lupoclient-0.0.1.dist-info/RECORD
