Metadata-Version: 2.1
Name: lupoclient
Version: 0.0.1
Summary: This client is a wrapper for the official Lupo API
Home-page: https://github.com/Staq-AI/zorro-client
Author: Michael Fatemi, Suhas Nandiraju
Author-email: myfatemi04@gmail.com
License: UNKNOWN
Platform: UNKNOWN
Classifier: Programming Language :: Python :: 3
Classifier: License :: OSI Approved :: MIT License
Classifier: Operating System :: OS Independent
Requires-Python: >=3.6
Requires-Dist: requests
